moonrakerpy/__init__.py
moonrakerpy/moonrakerpy.py
MoonrakerPy-0.2.2.dist-info/LICENSE
MoonrakerPy-0.2.2.dist-info/METADATA
MoonrakerPy-0.2.2.dist-info/WHEEL
MoonrakerPy-0.2.2.dist-info/top_level.txt
MoonrakerPy-0.2.2.dist-info/RECORD
