Metadata-Version: 2.1
Name: MoonrakerPy
Version: 0.2.2
Summary: A Python package for interface with the Moonraker API.
Home-page: https://github.com/alchemyEngine/MoonrakerPy
Author: Robert Pazdzior
Author-email: robertp@norbital.com
License: UNKNOWN
Platform: UNKNOWN
Classifier: Programming Language :: Python :: 3
Classifier: License :: OSI Approved :: GNU General Public License v3 or later (GPLv3+)
Classifier: Operating System :: OS Independent
Classifier: Development Status :: 3 - Alpha
Requires-Python: >=3.7.3
Requires-Dist: requests (>=2.26.0)
